dbfactor_analyzer/__init__.py
dbfactor_analyzer/analyze.py
dbfactor_analyzer/compat.py
dbfactor_analyzer/data_load.py
dbfactor_analyzer/exceptions.py
dbfactor_analyzer/performance.py
dbfactor_analyzer/plot_utils.py
dbfactor_analyzer/plotting.py
dbfactor_analyzer/pos.py
dbfactor_analyzer/prepare.py
dbfactor_analyzer/preprocess.py
dbfactor_analyzer/utils.py
dbfactor_analyzer/version.py
dbfactor_analyzer-1.1.20.dist-info/.DS_Store
dbfactor_analyzer-1.1.20.dist-info/METADATA
dbfactor_analyzer-1.1.20.dist-info/WHEEL
dbfactor_analyzer-1.1.20.dist-info/top_level.txt
dbfactor_analyzer-1.1.20.dist-info/RECORD
