Metadata-Version: 2.1
Name: dbfactor-analyzer
Version: 1.1.20
Summary: DBZQ single factor analyzer
Author: DBZQ
Author-email: xxli1017@foxmail.com
Maintainer: 
Maintainer-email: 
License: Apache License v2
Platform: all
Classifier: Programming Language :: Python
Classifier: Operating System :: Microsoft :: Windows
Classifier: Operating System :: Unix
Classifier: Programming Language :: Python :: 2.7
Classifier: Programming Language :: Python :: 3.4
Classifier: Programming Language :: Python :: 3.5
Classifier: Programming Language :: Python :: 3.6
Classifier: Programming Language :: Python :: 3.7
Classifier: Programming Language :: Python :: 3.8
